Metadata-Version: 2.1
Name: foggleio
Version: 1.7
Summary: Continuous deployment has never been easy but with the help of Foggle.io you can be one step closer
Home-page: http://foggle.io/
Author: Barend Erasmus
Author-email: hirebarend@gmail.com
License: MIT
Platform: UNKNOWN
